{    
    "type": "minecraft:crafting_shaped",
    "group": "covered_pipe",
    "pattern": [
        "xcx",
        "mpm",
        "xcx"
    ],
    "key": {        
        "x": {
            "item": "minestrapp:m_chiseled_stone",
            "data": 8
        },
        "c": {
            "item": "minestrapp:m_chunks",
            "data": 4
        },
        "m": {
            "item": "minestrapp:mud_ball"
        },
        "p": {
            "item": "minestrapp:pipe"
        }
     },
     "result": {
        "item": "minestrapp:covered_pipe_reefstone",
        "count": 1
     }  
}