{    
    "type": "forge:ore_shaped",
    "pattern": [
        "plp",
        "seg",
        "pmp"
    ],
    "key": {        
        "p": {
            "item": "minestrapp:glow_paste"
        },
        "l": {
            "item": "minecraft:sea_lantern"
        },
        "s": {
            "type": "forge:ore_dict",
            "ore": "blockSunstone"
        },
        "g": {
            "type": "forge:ore_dict",
            "ore": "glowstone"
        },
        "m": {
            "item": "minecraft:magma"
        },
        "e": {
            "type": "forge:ore_dict",
            "ore": "endstone"
        }
     },
     "result": {
        "item": "minestrapp:godstone"
     }  
}