{
    "display": {
        "icon": {
            "item": "minestrapp:hamburger"
        },
        "title": {
            "translate": "advancements.husbandry.sandwich.title"
        },
        "description": {
            "translate": "advancements.husbandry.sandwich.description"
        }
    },
    "parent": "minestrapp:husbandry/buns",
    "criteria": {
        "hamburger": {
            "trigger": "minecraft:inventory_changed",
            "conditions": {
                "items": [
                    {
                        "item": "minestrapp:hamburger"
                    }
                ]
            }
        },
        "pbj": {
            "trigger": "minecraft:inventory_changed",
            "conditions": {
                "items": [
                    {
                        "item": "minestrapp:pbj"
                    }
                ]
            }
        },
        "salmon_burger": {
            "trigger": "minecraft:inventory_changed",
            "conditions": {
                "items": [
                    {
                        "item": "minestrapp:salmon_burger"
                    }
                ]
            }
        },
        "blt": {
            "trigger": "minecraft:inventory_changed",
            "conditions": {
                "items": [
                    {
                        "item": "minestrapp:blt"
                    }
                ]
            }
        },
        "grilled_cheese": {
            "trigger": "minecraft:inventory_changed",
            "conditions": {
                "items": [
                    {
                        "item": "minestrapp:grilled_cheese"
                    }
                ]
            }
        },
        "cheeseburger": {
            "trigger": "minecraft:inventory_changed",
            "conditions": {
                "items": [
                    {
                        "item": "minestrapp:cheeseburger"
                    }
                ]
            }
        },
        "fish_sandwich": {
            "trigger": "minecraft:inventory_changed",
            "conditions": {
                "items": [
                    {
                        "item": "minestrapp:fish_sandwich"
                    }
                ]
            }
        },
        "mushroom_burger": {
            "trigger": "minecraft:inventory_changed",
            "conditions": {
                "items": [
                    {
                        "item": "minestrapp:mushroom_burger"
                    }
                ]
            }
        }
    },
    "requirements": [
        [
            "hamburger",
            "pbj",
            "salmon_burger",
            "blt",
            "grilled_cheese",
            "fish_sandwich",
            "cheeseburger",
            "mushroom_burger"
        ]
    ]
}