{
  "parent": "minecraft:recipes/root",
  "rewards": {
    "recipes": [
      "minestrapp:block_chiseled_shimmerstone"
    ]
  },
  "criteria": {
    "has_shimmerstone_slab": {
      "trigger": "minecraft:inventory_changed",
      "conditions": {
        "items": [
          {
            "item": "minestrapp:m_misc_stone_slab_1",
            "data": 6
          }
        ]
      }
    },
    "has_the_recipe": {
      "trigger": "minecraft:recipe_unlocked",
      "conditions": {
        "recipe": "minestrapp:block_chiseled_shimmerstone"
      }
    }
  },
  "requirements": [
    [
      "has_shimmerstone_slab",
      "has_the_recipe"
    ]
  ]
}