{
  "parent": "minecraft:recipes/root",
  "rewards": {
    "recipes": [
      "minestrapp:item_advanced_tech_doodad"
    ]
  },
  "criteria": {
    "has_doodad": {
      "trigger": "minecraft:inventory_changed",
      "conditions": {
        "items": [
          {
            "item": "minestrapp:m_tech_component",
            "data": 4
          }
        ]
      }
    },
    "has_the_recipe": {
      "trigger": "minecraft:recipe_unlocked",
      "conditions": {
        "recipe": "minestrapp:item_advanced_tech_doodad"
      }
    }
  },
  "requirements": [
    [
      "has_doodad",
      "has_the_recipe"
    ]
  ]
}